MANIFEST.in
README.rst
setup.cfg
setup.py
docs/HISTORY.txt
docs/INSTALL.txt
docs/LICENSE.GPL
docs/LICENSE.txt
plomino/__init__.py
plomino/__init__.pyc
plomino.leaflet.egg-info/PKG-INFO
plomino.leaflet.egg-info/SOURCES.txt
plomino.leaflet.egg-info/dependency_links.txt
plomino.leaflet.egg-info/entry_points.txt
plomino.leaflet.egg-info/namespace_packages.txt
plomino.leaflet.egg-info/not-zip-safe
plomino.leaflet.egg-info/requires.txt
plomino.leaflet.egg-info/top_level.txt
plomino/leaflet/__init__.py
plomino/leaflet/configure.zcml
plomino/leaflet/field.py
plomino/leaflet/leaflet_edit.pt
plomino/leaflet/leaflet_read.pt
plomino/leaflet/tests.py