Metadata-Version: 1.0
Name: plomino.leaflet
Version: 0.2dev
Summary: Leaflet/Plomino integration
Home-page: https://github.com/plomino/plomino.leaflet
Author: Eric BREHAULT
Author-email: eric.brehault@makina-corpus.org
License: GPL
Keywords: Plomino,leaflet
Platform: UNKNOWN
Classifier: Framework :: Plone
Classifier: Programming Language :: Python
